mailscript/__init__.py
mailscript/__main__.py
mailscript/config_template.py
mailscript/credentials.py
mailscript/mailer.py
mailscript/receiver.py
mailscript/templates/__init__.py
mailscript/templates/renderer.py
mailscript-0.2.1.dist-info/licenses/LICENSE
mailscript-0.2.1.dist-info/METADATA
mailscript-0.2.1.dist-info/WHEEL
mailscript-0.2.1.dist-info/top_level.txt
mailscript-0.2.1.dist-info/RECORD
