Metadata-Version: 2.4
Name: mailscript
Version: 0.2.1
Summary: A Python library for simplified email sending and receiving with secure credentials management
Home-page: https://rakshithkalmadi.github.io/mailscript/
Author: Rakshith Kalmadi
Author-email: rakshithkalmadi@gmail.com
Keywords: email,smtp,mail,template,html-email
Classifier: Development Status :: 3 - Alpha
Classifier: Intended Audience :: Developers
Classifier: License :: OSI Approved :: MIT License
Classifier: Programming Language :: Python :: 3
Classifier: Programming Language :: Python :: 3.7
Classifier: Programming Language :: Python :: 3.8
Classifier: Programming Language :: Python :: 3.9
Classifier: Programming Language :: Python :: 3.10
Classifier: Programming Language :: Python :: 3.11
Classifier: Topic :: Communications :: Email
Requires-Python: >=3.7
License-File: LICENSE
Requires-Dist: jinja2>=3.0.0
Provides-Extra: dev
Requires-Dist: pytest>=6.0.0; extra == "dev"
Requires-Dist: pytest-cov>=2.12.0; extra == "dev"
Requires-Dist: black>=21.5b2; extra == "dev"
Requires-Dist: flake8>=3.9.0; extra == "dev"
Dynamic: author
Dynamic: author-email
Dynamic: classifier
Dynamic: description
Dynamic: description-content-type
Dynamic: home-page
Dynamic: keywords
Dynamic: license-file
Dynamic: provides-extra
Dynamic: requires-dist
Dynamic: requires-python
Dynamic: summary
